<?xml version="1.0" encoding="UTF-8"?>
<con:soapui-project id="643d77b1-6e68-4625-88b8-e76681d3cec9" activeEnvironment="Default" name="DTC_Driver_Portal" resourceRoot="" soapui-version="5.2.0" abortOnError="false" runType="SEQUENTIAL" xmlns:con="http://eviware.com/soapui/config"><con:settings/><con:interface xsi:type="con:RestService" id="8f948276-edd1-4a20-976d-a8ca6ef7275f" wadlVersion="http://wadl.dev.java.net/2009/02" name="http://vedcdi.ds.newsint" type="rest" xmlns:xsi="http://www.w3.org/2001/XMLSchema-instance"><con:settings/><con:definitionCache/><con:endpoints><con:endpoint>http://vedcdi.ds.newsint</con:endpoint></con:endpoints><con:resource name="Login" path="/nuk/driverportal/api/1/login" id="1cd06761-f0ad-4501-89b7-34d071a9268a"><con:settings/><con:parameters/><con:method name="Login" id="5fc1bb29-b56f-4571-89ef-15c9e2f7ba86" method="POST"><con:settings/><con:parameters/><con:representation type="RESPONSE"><con:mediaType xsi:nil="true"/><con:status>0</con:status><con:params/><con:element>data</con:element></con:representation><con:representation type="FAULT"><con:mediaType>text/html; charset=iso-8859-1</con:mediaType><con:status>401</con:status><con:params/><con:element>html</con:element></con:representation><con:representation type="RESPONSE"><con:mediaType>text/html</con:mediaType><con:status>200</con:status><con:params/></con:representation><con:representation type="REQUEST"><con:mediaType>application/json</con:mediaType><con:params/></con:representation><con:request name="Request 1" id="e572dfd6-0e7a-4be9-b9bd-9a0576cc03f0" mediaType="application/json" postQueryString="false"><con:settings><con:setting id="com.eviware.soapui.impl.wsdl.WsdlRequest@request-headers">&lt;xml-fragment/></con:setting></con:settings><con:endpoint>http://vecdci.ds.newsint</con:endpoint><con:request>{
	"username": "MTURNER1",
	"password": "mypassword"
}
</con:request><con:originalUri>http://vedcdi.ds.newsint/nuk/driverportal/api/1/login</con:originalUri><con:credentials><con:authType>No Authorization</con:authType></con:credentials><con:jmsConfig JMSDeliveryMode="PERSISTENT"/><con:jmsPropertyConfig/><con:parameters/></con:request></con:method></con:resource></con:interface><con:properties/><con:wssContainer/><con:oAuth2ProfileContainer/></con:soapui-project>